mdca/__init__.py
mdca/__main__.py
mdca/analyzer/BinMerger.py
mdca/analyzer/DataPreprocessor.py
mdca/analyzer/Index.py
mdca/analyzer/MCTSTree.py
mdca/analyzer/MCTSTreeNode.py
mdca/analyzer/MultiDimensionalAnalyzer.py
mdca/analyzer/ResultCluster.py
mdca/analyzer/ResultPath.py
mdca/analyzer/chi2_filter.py
mdca/analyzer/commons.py
mdca-0.1.21.dist-info/METADATA
mdca-0.1.21.dist-info/WHEEL
mdca-0.1.21.dist-info/entry_points.txt
mdca-0.1.21.dist-info/top_level.txt
mdca-0.1.21.dist-info/RECORD
