Metadata-Version: 2.4
Name: mdca
Version: 0.1.21
Summary: MDCA: Multi-dimensional Data Combination Analysis. It's used to analysis data table through multi-dimensional data combinations. Multi-dimensional distribution, fairness, and model error analysis are supported.
Author-email: jingjiajie <932166095@qq.com>
Maintainer-email: jingjiajie <932166095@qq.com>
Project-URL: Homepage, https://github.com/jingjiajie/mdca
Project-URL: Repository, https://github.com/jingjiajie/mdca.git
Project-URL: Bug Tracker, https://github.com/jingjiajie/mdca/issues
Keywords: multi-dimensional,multidimensional,distribution,fairness,model fairness,error analysis,model error,model error analysis
Requires-Python: >=3.8
Requires-Dist: bitarray==3.1.0
Requires-Dist: numpy==2.2.3
Requires-Dist: pandas==2.2.3
Requires-Dist: scipy==1.15.2
